nl2sh/cli.py
nl2sh/utils.py
nl2sh/models/__init__.py
nl2sh/models/config.py
nl2sh/models/model.py
nl2sh/server/__init__.py
nl2sh/server/server.py
nl2sh/server/utils.py
nl2sh-0.1.4.dist-info/METADATA
nl2sh-0.1.4.dist-info/WHEEL
nl2sh-0.1.4.dist-info/entry_points.txt
nl2sh-0.1.4.dist-info/top_level.txt
nl2sh-0.1.4.dist-info/RECORD
