Metadata-Version: 2.4
Name: nl2sh
Version: 0.1.4
Summary: NL2SH tool using small language models.
Author-email: Giovanni Belval <giovanni.belval@icloud.com>
Requires-Python: >=3.12
Requires-Dist: fastapi[standard]
Requires-Dist: uvicorn
Requires-Dist: transformers
Requires-Dist: torch
Requires-Dist: accelerate
Requires-Dist: rich
Requires-Dist: json-repair
Requires-Dist: peft
Requires-Dist: platformdirs
